plone.distribution-3.2.1-py3.13-nspkg.pth
plone/distribution/__init__.py
plone/distribution/configure.zcml
plone/distribution/core.py
plone/distribution/handler.py
plone/distribution/interfaces.py
plone/distribution/meta.zcml
plone/distribution/metaconfigure.py
plone/distribution/registry.py
plone/distribution/api/__init__.py
plone/distribution/api/distribution.py
plone/distribution/api/site.py
plone/distribution/browser/__init__.py
plone/distribution/browser/admin.py
plone/distribution/browser/configure.zcml
plone/distribution/browser/image.py
plone/distribution/browser/overrides.zcml
plone/distribution/browser/static/plone-logo.png
plone/distribution/browser/static/plone-overview.min.css
plone/distribution/browser/static/plone-overview.min.js
plone/distribution/browser/static/plone.svg
plone/distribution/browser/templates/plone-overview.pt
plone/distribution/cli/__init__.py
plone/distribution/default/__init__.py
plone/distribution/default/image.png
plone/distribution/default/schema.json
plone/distribution/services/__init__.py
plone/distribution/services/configure.zcml
plone/distribution/services/overrides.zcml
plone/distribution/services/auth/__init__.py
plone/distribution/services/auth/configure.zcml
plone/distribution/services/auth/login.py
plone/distribution/services/sites/__init__.py
plone/distribution/services/sites/add.py
plone/distribution/services/sites/configure.zcml
plone/distribution/services/sites/get.py
plone/distribution/services/system/__init__.py
plone/distribution/services/system/configure.zcml
plone/distribution/services/system/get.py
plone/distribution/testing/__init__.py
plone/distribution/testing/configure.zcml
plone/distribution/testing/layer.py
plone/distribution/testing/testing.py
plone/distribution/testing/distributions/default/image.png
plone/distribution/testing/distributions/default/profiles.json
plone/distribution/testing/distributions/default/schema.json
plone/distribution/testing/distributions/default/content/discussions.json
plone_distribution-3.2.1.dist-info/licenses/LICENSE
plone_distribution-3.2.1.dist-info/METADATA
plone_distribution-3.2.1.dist-info/WHEEL
plone_distribution-3.2.1.dist-info/entry_points.txt
plone_distribution-3.2.1.dist-info/namespace_packages.txt
plone_distribution-3.2.1.dist-info/top_level.txt
plone_distribution-3.2.1.dist-info/RECORD
