Metadata-Version: 2.4
Name: plone.distribution
Version: 3.2.1
Summary: Plone distribution support
Home-page: https://plone.org
Author: Plone Foundation
Author-email: releasemanager@plone.org
License: GPL version 2
Project-URL: Homepage, https://plone.org
Project-URL: Documentation, https://6.docs.plone.org
Project-URL: Source, https://github.com/plone/plone.distribution
Project-URL: Issues, https://github.com/plone/plone.distribution/issues
Keywords: Plone CMF Python Zope CMS Distribution
Classifier: Development Status :: 3 - Alpha
Classifier: Environment :: Web Environment
Classifier: Framework :: Plone
Classifier: Framework :: Plone :: 6.0
Classifier: Framework :: Plone :: Core
Classifier: Framework :: Zope :: 5
Classifier: License :: OSI Approved :: GNU General Public License v2 (GPLv2)
Classifier: Operating System :: OS Independent
Classifier: Programming Language :: Python
Classifier: Programming Language :: Python :: 3.8
Classifier: Programming Language :: Python :: 3.9
Classifier: Programming Language :: Python :: 3.10
Classifier: Programming Language :: Python :: 3.11
Requires-Python: >=3.8
License-File: LICENSE
Requires-Dist: Products.CMFPlone
Requires-Dist: Products.GenericSetup
Requires-Dist: Zope
Requires-Dist: setuptools
Requires-Dist: jsonschema
Requires-Dist: plone.api
Requires-Dist: plone.base
Requires-Dist: plone.dexterity
Requires-Dist: plone.exportimport>=1.0.0b1
Requires-Dist: plone.i18n
Requires-Dist: plone.protect
Requires-Dist: plone.rest
Requires-Dist: plone.restapi
Requires-Dist: z3c.unconfigure
Provides-Extra: test
Requires-Dist: plone.app.iterate; extra == "test"
Requires-Dist: plone.app.testing; extra == "test"
Requires-Dist: plone.app.upgrade; extra == "test"
Requires-Dist: plone.restapi[test]; extra == "test"
Requires-Dist: plone.volto[test]; extra == "test"
Requires-Dist: plone.testing; extra == "test"
Requires-Dist: pytest-cov; extra == "test"
Requires-Dist: pytest-plone>=0.5.0; extra == "test"
Requires-Dist: pytest; extra == "test"
Requires-Dist: zest.releaser[recommended]; extra == "test"
Requires-Dist: zestreleaser.towncrier; extra == "test"
Dynamic: author
Dynamic: author-email
Dynamic: classifier
Dynamic: description
Dynamic: description-content-type
Dynamic: home-page
Dynamic: keywords
Dynamic: license
Dynamic: license-file
Dynamic: project-url
Dynamic: provides-extra
Dynamic: requires-dist
Dynamic: requires-python
Dynamic: summary
